xiongmao/__init__.py
xiongmao-0.0.3.dist-info/LICENCE
xiongmao-0.0.3.dist-info/METADATA
xiongmao-0.0.3.dist-info/WHEEL
xiongmao-0.0.3.dist-info/top_level.txt
xiongmao-0.0.3.dist-info/RECORD
