Metadata-Version: 2.1
Name: xiongmao
Version: 0.0.3
Summary: Binding Pandas functions to dataframe as methods
Home-page: https://github.com/johnlichtenstein/xiongmao
Author: Johnny Lichtenstein
Author-email: johnlichtenstein@gmail.com
License: UNKNOWN
Download-URL: https://github.com/johnlichtenstein/xiongmao/archive/0.0.3.tar.gz
Platform: UNKNOWN
Classifier: Programming Language :: Python :: 3
Classifier: License :: OSI Approved :: MIT License
Classifier: Operating System :: OS Independent
Requires-Python: >=3.5
